navaltoolbox/__init__.py
navaltoolbox/navaltoolbox.cpython-39-darwin.so
navaltoolbox/navaltoolbox.pyi
navaltoolbox/plotting.py
navaltoolbox/py.typed
navaltoolbox/visualization.py
navaltoolbox-0.3.0.dist-info/METADATA
navaltoolbox-0.3.0.dist-info/WHEEL
navaltoolbox-0.3.0.dist-info/RECORD
