Metadata-Version: 2.4
Name: navaltoolbox
Version: 0.3.0
Classifier: Development Status :: 3 - Alpha
Classifier: Intended Audience :: Science/Research
Classifier: License :: OSI Approved :: GNU Affero General Public License v3 or later (AGPLv3+)
Classifier: Programming Language :: Python :: 3
Classifier: Programming Language :: Python :: 3.9
Classifier: Programming Language :: Python :: 3.10
Classifier: Programming Language :: Python :: 3.11
Classifier: Programming Language :: Python :: 3.12
Classifier: Programming Language :: Python :: 3.13
Classifier: Programming Language :: Rust
Classifier: Topic :: Scientific/Engineering
Requires-Dist: plotly>=5.0.0
Requires-Dist: numpy>=1.20.0
Summary: High-performance naval architecture library for hydrostatics, stability, and tank calculations
Keywords: naval-architecture,hydrostatics,stability,marine-engineering,ship-design
Home-Page: https://github.com/NavalToolbox/navaltoolbox-lib
Author: Antoine ANCEAU
License: AGPL-3.0-or-later
Requires-Python: >=3.9
Project-URL: Documentation, https://navaltoolbox.github.io/navaltoolbox-lib
Project-URL: Homepage, https://www.navaltoolbox.com
Project-URL: Issues, https://github.com/NavalToolbox/navaltoolbox-lib/issues
Project-URL: Repository, https://github.com/NavalToolbox/navaltoolbox-lib
